README.md
setup.py
cxutils/__init__.py
cxutils/directory.py
cxutils/version.py
cxutils.egg-info/PKG-INFO
cxutils.egg-info/SOURCES.txt
cxutils.egg-info/dependency_links.txt
cxutils.egg-info/top_level.txt