Metadata-Version: 1.0
Name: cxutils
Version: 0.0.4
Summary: Convenient utilities
Home-page: https://github.com/cx1111/cxutils
Author: Chen Xie
Author-email: is.chenx@gmail.com
License: MIT
Keywords: convenience
Platform: UNKNOWN
